conduit_pkg/__init__.py
conduit_pkg/client.py
bpcs_conduit-0.0.9.dist-info/LICENSE
bpcs_conduit-0.0.9.dist-info/METADATA
bpcs_conduit-0.0.9.dist-info/WHEEL
bpcs_conduit-0.0.9.dist-info/top_level.txt
bpcs_conduit-0.0.9.dist-info/RECORD
