Metadata-Version: 2.1
Name: bpcs-conduit
Version: 0.0.9
Summary: Python SDK for BPCS Conduit data virtualization tool
Home-page: https://github.com/BlueprintConsulting/Conduit-PythonSDK
Author: Allen Plummer
Author-email: ahplummer@gmail.com
License: UNKNOWN
Project-URL: Bug Tracker, https://github.com/BlueprintConsulting/Conduit-PythonSDK/issues
Platform: UNKNOWN
Classifier: Programming Language :: Python :: 3
Classifier: License :: OSI Approved :: MIT License
Classifier: Operating System :: OS Independent
Requires-Python: >=3.6
Requires-Dist: requests
Requires-Dist: urllib3
